LICENSE
MANIFEST.in
README.rst
requirements.txt
setup.py
log2seq/__init__.py
log2seq/__main__.py
log2seq/_common.py
log2seq/header.py
log2seq/preset.py
log2seq/statement.py
log2seq.egg-info/PKG-INFO
log2seq.egg-info/SOURCES.txt
log2seq.egg-info/dependency_links.txt
log2seq.egg-info/requires.txt
log2seq.egg-info/top_level.txt