Metadata-Version: 2.1
Name: log2seq
Version: 0.2.6
Summary: A tool to parse syslog-like messages into word sequences
Home-page: https://github.com/cpflat/log2seq/
Author: Satoru Kobayashi
Author-email: sat@nii.ac.jp
License: BSD 3-Clause "New" or "Revised" License
Platform: UNKNOWN
Classifier: Development Status :: 4 - Beta
Classifier: Environment :: Console
Classifier: Intended Audience :: Information Technology
Classifier: Intended Audience :: Science/Research
Classifier: Intended Audience :: Developers
Classifier: License :: OSI Approved :: BSD License
Classifier: Operating System :: OS Independent
Classifier: Programming Language :: Python :: 3.7
Classifier: Programming Language :: Python :: 3.8
Classifier: Topic :: Scientific/Engineering :: Information Analysis
Classifier: Topic :: Software Development :: Libraries :: Python Modules
License-File: LICENSE
